ghostinspector.py
ghostinspector-0.0.1.dist-info/METADATA
ghostinspector-0.0.1.dist-info/WHEEL
ghostinspector-0.0.1.dist-info/top_level.txt
ghostinspector-0.0.1.dist-info/RECORD
