Metadata-Version: 2.1
Name: ghostinspector
Version: 0.0.1
Summary: tools for using the ghostInsepctor API
Home-page: UNKNOWN
Author: UNKNOWN
Author-email: UNKNOWN
License: UNKNOWN
Platform: UNKNOWN
